kirlent_docutils/__init__.py
kirlent_docutils/html5.py
kirlent_docutils/impressjs.css
kirlent_docutils/impressjs.py
kirlent_docutils/kirlent_html5.css
kirlent_docutils/kirlent_impressjs.css
kirlent_docutils/kirlent_revealjs.css
kirlent_docutils/kirlent_slides.css
kirlent_docutils/minimal.css
kirlent_docutils/plain.css
kirlent_docutils/revealjs.css
kirlent_docutils/revealjs.py
kirlent_docutils/slides.css
kirlent_docutils/slides.py
kirlent_docutils/slides_base.css
kirlent_docutils/utils.py
kirlent_docutils/bundled/MathJax.min.js
kirlent_docutils/bundled/impress.js
kirlent_docutils/bundled/reveal-notes.js
kirlent_docutils/bundled/reveal.js
kirlent_docutils/bundled/rough-notation.iife.js
kirlent_docutils-0.4.dist-info/entry_points.txt
kirlent_docutils-0.4.dist-info/LICENSE.txt
kirlent_docutils-0.4.dist-info/WHEEL
kirlent_docutils-0.4.dist-info/METADATA
kirlent_docutils-0.4.dist-info/RECORD
